pestifer/__init__.py
pestifer/charmmff/__init__.py
pestifer/charmmff/charmmffcontent.py
pestifer/charmmff/charmmfftop.py
pestifer/charmmff/graphhelpers.py
pestifer/charmmff/make_pdb_collection.py
pestifer/charmmff/pdbrepository.py
pestifer/core/__init__.py
pestifer/core/artifacts.py
pestifer/core/baseobj.py
pestifer/core/command.py
pestifer/core/config.py
pestifer/core/controller.py
pestifer/core/example.py
pestifer/core/examplemanager.py
pestifer/core/labels.py
pestifer/core/objmanager.py
pestifer/core/pestifer.py
pestifer/core/pipeline.py
pestifer/core/resourcemanager.py
pestifer/logparsers/__init__.py
pestifer/logparsers/logparser.py
pestifer/logparsers/namdlogparser.py
pestifer/logparsers/packmollogparser.py
pestifer/logparsers/pdb2pqrlogparser.py
pestifer/logparsers/psfgenlogparser.py
pestifer/molecule/__init__.py
pestifer/molecule/asymmetricunit.py
pestifer/molecule/atom.py
pestifer/molecule/bilayer.py
pestifer/molecule/bioassemb.py
pestifer/molecule/chainidmanager.py
pestifer/molecule/molecule.py
pestifer/molecule/residue.py
pestifer/molecule/segment.py
pestifer/molecule/stateinterval.py
pestifer/molecule/transform.py
pestifer/objs/__init__.py
pestifer/objs/cfusion.py
pestifer/objs/cleavagesite.py
pestifer/objs/crot.py
pestifer/objs/deletion.py
pestifer/objs/graft.py
pestifer/objs/insertion.py
pestifer/objs/link.py
pestifer/objs/mutation.py
pestifer/objs/orient.py
pestifer/objs/patch.py
pestifer/objs/resid.py
pestifer/objs/rottrans.py
pestifer/objs/seqadv.py
pestifer/objs/ssbond.py
pestifer/objs/ssbonddelete.py
pestifer/objs/substitution.py
pestifer/objs/ter.py
pestifer/psfutil/__init__.py
pestifer/psfutil/psfangle.py
pestifer/psfutil/psfatom.py
pestifer/psfutil/psfbond.py
pestifer/psfutil/psfcontents.py
pestifer/psfutil/psfdihedral.py
pestifer/psfutil/psfpatch.py
pestifer/psfutil/psfremark.py
pestifer/psfutil/psfring.py
pestifer/psfutil/psftopoelement.py
pestifer/resources/__init__.py
pestifer/resources/charmmff/toppar_c36_jul24.tgz
pestifer-2.1.6.dist-info/METADATA
pestifer-2.1.6.dist-info/WHEEL
pestifer-2.1.6.dist-info/entry_points.txt
pestifer-2.1.6.dist-info/licenses/LICENSE
pestifer-2.1.6.dist-info/RECORD
