Metadata-Version: 2.4
Name: pestifer
Version: 2.1.6
Summary: A NAMD topology/coordinate system preparation tool
Project-URL: Source, https://github.com/cameronabrams/pestifer
Project-URL: Documentation, https://pestifer.readthedocs.io/en/latest/
Project-URL: Bug Tracker, https://github.com/cameronabrams/pestifer/issues
Author-email: Cameron F Abrams <cfa22@drexel.edu>
License-File: LICENSE
Classifier: License :: OSI Approved :: MIT License
Classifier: Operating System :: POSIX :: Linux
Classifier: Programming Language :: Python :: 3
Requires-Python: >=3.12
Requires-Dist: colorist
Requires-Dist: docutils<0.22,>=0.20
Requires-Dist: filelock
Requires-Dist: fsspec
Requires-Dist: gputil
Requires-Dist: joblib
Requires-Dist: matplotlib
Requires-Dist: mmcif
Requires-Dist: networkx
Requires-Dist: numpy>=1.24
Requires-Dist: pandas
Requires-Dist: pidibble>=1.5.2
Requires-Dist: platformdirs
Requires-Dist: progressbar2
Requires-Dist: pydantic
Requires-Dist: pyyaml>=6
Requires-Dist: scipy
Requires-Dist: sphinx>=8.2.3
Requires-Dist: unidiff
Requires-Dist: ycleptic>=2.0.1
